[
  {
    "payeeName": "John Doe",
    "address": "123 Main Street",
    "state": "California",
    "zipCode": "90001",
    "phone": "081234567890",
    "account": "123456789",
    "accountVerify": "123456789",
    "amount": "100",
    "accountBank": "12345"
  },
  {
    "payeeName": "Jane Smith",
    "address": "456 Oak Avenue",
    "state": "Texas",
    "zipCode": "75001",
    "phone": "082345678901",
    "account": "987654321",
    "accountVerify": "987654321",
    "amount": "250",
    "accountBank": "12345"
  },
  {
    "payeeName": "Michael Johnson",
    "address": "789 Pine Road",
    "state": "Florida",
    "zipCode": "33101",
    "phone": "083456789012",
    "account": "555666777",
    "accountVerify": "555666777",
    "amount": "500",
    "accountBank": "12345"
  },
  {
    "payeeName": "Sarah Williams",
    "address": "321 Maple Drive",
    "state": "New York",
    "zipCode": "10001",
    "phone": "084567890123",
    "account": "111222333",
    "accountVerify": "111222333",
    "amount": "1000",
    "accountBank": "12345"
  },
  {
    "payeeName": "David Brown",
    "address": "654 Cedar Lane",
    "state": "Nevada",
    "zipCode": "88901",
    "phone": "085678901234",
    "account": "999888777",
    "accountVerify": "999888777",
    "amount": "1500",
    "accountBank": "12345"
  }
]